strato_dyndns/__init__.py
strato_dyndns/main.py
strato_dyndns/clients/__init__.py
strato_dyndns/clients/connection_handler.py
strato_dyndns/clients/dyndns_client.py
strato_dyndns/clients/namecheap_client.py
strato_dyndns/clients/strato_client.py
strato_dyndns/lib/__init__.py
strato_dyndns/lib/args_validator.py
strato_dyndns/lib/file_operations.py
strato_dyndns/lib/requests_wrapper.py
strato_dyndns/schema/__init__.py
strato_dyndns/schema/namecheap.py
strato_dyndns/schema/strato.py
strato_dyndns-2.3.3.dist-info/LICENSE
strato_dyndns-2.3.3.dist-info/METADATA
strato_dyndns-2.3.3.dist-info/WHEEL
strato_dyndns-2.3.3.dist-info/entry_points.txt
strato_dyndns-2.3.3.dist-info/top_level.txt
strato_dyndns-2.3.3.dist-info/RECORD
