Metadata-Version: 2.1
Name: strato_dyndns
Version: 2.3.3
Summary: Updates your DNS records on supported DNS registrars.
Home-page: https://github.com/regmibijay/strato-dyndns
Author: Bijay Regmi
Author-email: strato-dyndns@regdelivery.de
License: GNU (GPLv3)
Classifier: Programming Language :: Python :: 3
Classifier: License :: OSI Approved :: GNU General Public License v3 (GPLv3)
Classifier: Operating System :: OS Independent
Requires-Python: >=3.6
License-File: LICENSE
Requires-Dist: requests
